pythaiair/__init__.py
test/__init__.py
pythaiair-0.2.dist-info/LICENSE
pythaiair-0.2.dist-info/METADATA
pythaiair-0.2.dist-info/WHEEL
pythaiair-0.2.dist-info/top_level.txt
pythaiair-0.2.dist-info/RECORD
